Python3Opencv4JisuanjiShijueXuexiShouceChuyiFix1/README.md
Python3Opencv4JisuanjiShijueXuexiShouceChuyiFix1/__init__.py
Python3Opencv4JisuanjiShijueXuexiShouceChuyiFix1/__main__.py
Python3Opencv4JisuanjiShijueXuexiShouceChuyiFix1/file.epub
Python3Opencv4JisuanjiShijueXuexiShouceChuyiFix1/index.html
Python3Opencv4JisuanjiShijueXuexiShouceChuyiFix1/css/__init__.py
Python3Opencv4JisuanjiShijueXuexiShouceChuyiFix1/css/annotations.css
Python3Opencv4JisuanjiShijueXuexiShouceChuyiFix1/css/main.css
Python3Opencv4JisuanjiShijueXuexiShouceChuyiFix1/css/normalize.css
Python3Opencv4JisuanjiShijueXuexiShouceChuyiFix1/css/popup.css
Python3Opencv4JisuanjiShijueXuexiShouceChuyiFix1/font/__init__.py
Python3Opencv4JisuanjiShijueXuexiShouceChuyiFix1/font/fontello.eot
Python3Opencv4JisuanjiShijueXuexiShouceChuyiFix1/font/fontello.svg
Python3Opencv4JisuanjiShijueXuexiShouceChuyiFix1/font/fontello.ttf
Python3Opencv4JisuanjiShijueXuexiShouceChuyiFix1/font/fontello.woff
Python3Opencv4JisuanjiShijueXuexiShouceChuyiFix1/img/__init__.py
Python3Opencv4JisuanjiShijueXuexiShouceChuyiFix1/img/annotator-glyph-sprite.png
Python3Opencv4JisuanjiShijueXuexiShouceChuyiFix1/img/annotator-icon-sprite.png
Python3Opencv4JisuanjiShijueXuexiShouceChuyiFix1/img/apple-touch-icon.png
Python3Opencv4JisuanjiShijueXuexiShouceChuyiFix1/img/cancelfullscreen.png
Python3Opencv4JisuanjiShijueXuexiShouceChuyiFix1/img/close.png
Python3Opencv4JisuanjiShijueXuexiShouceChuyiFix1/img/fullscreen.png
Python3Opencv4JisuanjiShijueXuexiShouceChuyiFix1/img/loader.gif
Python3Opencv4JisuanjiShijueXuexiShouceChuyiFix1/img/menu-icon.png
Python3Opencv4JisuanjiShijueXuexiShouceChuyiFix1/img/save.png
Python3Opencv4JisuanjiShijueXuexiShouceChuyiFix1/img/saved.png
Python3Opencv4JisuanjiShijueXuexiShouceChuyiFix1/img/settings-s.png
Python3Opencv4JisuanjiShijueXuexiShouceChuyiFix1/img/settings.png
Python3Opencv4JisuanjiShijueXuexiShouceChuyiFix1/img/star.png
Python3Opencv4JisuanjiShijueXuexiShouceChuyiFix1/js/__init__.py
python3_opencv4_jisuanji_shijue_xuexi_shouce_chuyi_fix1-2025.3.25.0.dist-info/METADATA
python3_opencv4_jisuanji_shijue_xuexi_shouce_chuyi_fix1-2025.3.25.0.dist-info/WHEEL
python3_opencv4_jisuanji_shijue_xuexi_shouce_chuyi_fix1-2025.3.25.0.dist-info/entry_points.txt
python3_opencv4_jisuanji_shijue_xuexi_shouce_chuyi_fix1-2025.3.25.0.dist-info/top_level.txt
python3_opencv4_jisuanji_shijue_xuexi_shouce_chuyi_fix1-2025.3.25.0.dist-info/RECORD
